jupylint/__init__.py
jupylint/__main__.py
jupylint/_test.py
jupylint/_test_template.py
jupylint/jupylint.py
jupylint-2.2.4.dist-info/LICENSE
jupylint-2.2.4.dist-info/METADATA
jupylint-2.2.4.dist-info/WHEEL
jupylint-2.2.4.dist-info/entry_points.txt
jupylint-2.2.4.dist-info/top_level.txt
jupylint-2.2.4.dist-info/RECORD
