Metadata-Version: 2.1
Name: jupylint
Version: 2.2.4
Summary: A tool to run pylint on Jupyter notebooks
Home-page: https://github.com/EdmundGoodman/Jupyter_Pylinter
Download-URL: https://github.com/EdmundGoodman/Jupyter_Pylinter/archive/refs/tags/v2.2.4.tar.gz
Author: Edmund Goodman
Author-email: egoodman3141@gmail.com
License: MIT
Keywords: Jupyter,Pylint,linter
Classifier: Development Status :: 7 - Inactive
Classifier: Intended Audience :: Developers
Classifier: Topic :: Software Development :: Build Tools
Classifier: License :: OSI Approved :: MIT License
Classifier: Programming Language :: Python :: 3
Classifier: Programming Language :: Python :: 3.4
Classifier: Programming Language :: Python :: 3.5
Classifier: Programming Language :: Python :: 3.6
License-File: LICENSE
Requires-Dist: pylint
